containerimage_py-1.1.3.dist-info/licenses/LICENSE
image/__init__.py
image/auth.py
image/byteunit.py
image/client.py
image/config.py
image/configschema.py
image/containerimage.py
image/containerimageinspect.py
image/descriptor.py
image/errors.py
image/inspectschema.py
image/linter.py
image/manifest.py
image/manifestfactory.py
image/manifestlist.py
image/manifestlistentry.py
image/manifestschema.py
image/mediatypes.py
image/oci.py
image/ocischema.py
image/platform.py
image/reference.py
image/regex.py
image/v2s2.py
image/v2s2schema.py
image/cli/cli.py
containerimage_py-1.1.3.dist-info/METADATA
containerimage_py-1.1.3.dist-info/WHEEL
containerimage_py-1.1.3.dist-info/entry_points.txt
containerimage_py-1.1.3.dist-info/top_level.txt
containerimage_py-1.1.3.dist-info/RECORD
