Metadata-Version: 2.4
Name: containerimage-py
Version: 1.1.3
Summary: A python library for ineracting with container images and container image registries
Author-email: Ethan Balcik <ethanbalcik@ibm.com>
License-Expression: Apache-2.0
Project-URL: Homepage, https://github.com/whatsacomputertho/containerimage-py
Project-URL: Issues, https://github.com/whatsacomputertho/containerimage-py/issues
Keywords: container,image,py,oci,docker
Classifier: Programming Language :: Python :: 3
Classifier: Operating System :: OS Independent
Requires-Python: >=3.9
License-File: LICENSE
Requires-Dist: requests
Requires-Dist: jsonschema
Requires-Dist: artifact-lint-py
Provides-Extra: test
Requires-Dist: tox; extra == "test"
Requires-Dist: pytest; extra == "test"
Requires-Dist: pytest-mock; extra == "test"
Requires-Dist: pytest-cov; extra == "test"
Provides-Extra: build
Requires-Dist: build; extra == "build"
Provides-Extra: doc
Requires-Dist: sphinx; extra == "doc"
Requires-Dist: sphinx_rtd_theme; extra == "doc"
Dynamic: license-file
